exereverse/__init__.py
exereverse/cli.py
exereverse/extractor.py
exereverse/post_install.py
exereverse/pyinstxtractor.py
reversepi/__init__.py
reversepi/cli.py
reversepi/decompiler.py
reversepi/extractor.py
reversepi/post_install.py
reversepi/pyinstxtractor.py
exereverse-1.1.3.dist-info/METADATA
exereverse-1.1.3.dist-info/WHEEL
exereverse-1.1.3.dist-info/entry_points.txt
exereverse-1.1.3.dist-info/top_level.txt
exereverse-1.1.3.dist-info/RECORD
