Metadata-Version: 2.1
Name: exereverse
Version: 1.1.3
Summary: A tool to extract PyInstaller executables
Home-page: https://github.com/ByteBreach/exereverse
Author: MrFida
Author-email: mrfidal@proton.me
Classifier: Programming Language :: Python :: 3
Classifier: License :: OSI Approved :: MIT License
Classifier: Operating System :: OS Independent
Requires-Python: >=3.6
